{
  "template_type": "project_initialization_metadata",
  "version": "2.0",
  "project_info": {
    "name": "{{project_name}}",
    "client": "{{client_name}}",
    "start_date": "{{start_date}}",
    "objective": "{{objective_summary}}"
  },
  "roles": {
    "manager": "{{manager_name}}",
    "manager_email": "{{manager_email}}",
    "auditor_role": "{{auditor_role}}"
  },
  "technical_context": {
    "stack": "{{technology_stack}}",
    "changelog_file": "Analysis_{{date}}_{{time}}.md"
  },
  "audit_trail": {
    "reason": "{{audit_reason}}",
    "linked_agents": [],
    "linked_skills": [],
    "linked_checklists": []
  }
}
